[
  {
    "id": "V01",
    "type": "E-Scooter",
    "companyId": "C01",
    "condition": 84,
    "batteryCondition": 89,
    "status": "Active",
    "batteryLevel": 74
  },
  {
    "id": "V02",
    "type": "E-Scooter",
    "companyId": "C02",
    "condition": 32,
    "batteryCondition": 49,
    "status": "Active",
    "batteryLevel": 74
  },
  {
    "id": "V03",
    "type": "E-Scooter",
    "companyId": "C01",
    "condition": 90,
    "batteryCondition": 94,
    "status": "Inactive",
    "currentPosition": {
      "lat": 49.0025,
      "lng": 8.38591
    },
    "batteryLevel": 56
  },
  {
    "id": "V04",
    "type": "Train",
    "companyId": "C03",
    "status": "Active"
  },
  {
    "id": "V05",
    "type": "Train",
    "companyId": "C03",
    "status": "Active"
  },
  {
    "id": "V06",
    "type": "Train",
    "companyId": "C03",
    "status": "Active"
  }
]
